oxforddictionaries/__init__.py
oxforddictionaries/api.py
oxforddictionaries/words.py
oxforddictionaries-0.1.101.dist-info/METADATA
oxforddictionaries-0.1.101.dist-info/RECORD
oxforddictionaries-0.1.101.dist-info/WHEEL
oxforddictionaries-0.1.101.dist-info/top_level.txt
