Metadata-Version: 2.1
Name: oxforddictionaries
Version: 0.1.101
Summary: A python wrapper for the Oxford Dictionaries API.
Home-page: https://github.com/RafaelBroseghini/OxfordAPI
Author: Rafael Broseghini
Author-email: rafaellopesbroseghini@gmail.com
License: UNKNOWN
Project-URL: API Source, https://developer.oxforddictionaries.com/
Project-URL: Source, https://github.com/RafaelBroseghini/OxfordAPI
Keywords: words synonyms antonyms definitions
Platform: UNKNOWN
Classifier: Development Status :: 3 - Alpha
Classifier: Intended Audience :: Developers
Classifier: Topic :: Software Development :: Build Tools
Classifier: License :: OSI Approved :: MIT License
Classifier: Programming Language :: Python :: 3
Classifier: Programming Language :: Python :: 3.4
Classifier: Programming Language :: Python :: 3.5
Classifier: Programming Language :: Python :: 3.6
Requires-Dist: requests
